<?xml version="1.0"?>

<model>
  <load_pre>
    <image sym="left">vikings/erik/erik_stand_left.tga</image>
    <image sym="right">vikings/erik/erik_stand_right.tga</image>
    <image sym="climb">vikings/erik/erik_climbing.tga</image>
  </load_pre>

  <states>
    <state name="onground_standing_left" sym="left"/>
    <state name="onground_standing_right" sym="right"/>
    <state name="onground_moving_left" sym="left"/>
    <state name="onground_moving_right" sym="right"/>

    <state name="onground_knocked-out_left" image="erik_ko_left.png"/>
    <state name="onground_knocked-out_right" image="erik_ko_right.png"/>

    <state name="falling_standing_right" sym="right"/>
    <state name="falling_standing_left" sym="left"/>
    <state name="falling_moving_right" sym="right"/>
    <state name="falling_moving_left" sym="left"/>
    <state name="falling_jumping_left" sym="left"/>
    <state name="falling_jumping_right" sym="right"/>

    <state name="rising_standing_left" sym="left"/>
    <state name="rising_standing_right" sym="right"/>
    <state name="rising_moving_left" sym="left"/>
    <state name="rising_moving_right" sym="right"/>

    <state name="onground_jumping_left" sym="left"/>
    <state name="onground_jumping_right" sym="right"/>

    <state name="climbingUp_standing_left" sym="climb"/>
    <state name="climbingDown_standing_left" sym="climb"/>
    <state name="climbingRest_standing_left" sym="climb"/>

    <state name="climbingUp_standing_right" sym="climb"/>
    <state name="climbingDown_standing_right" sym="climb"/>
    <state name="climbingRest_standing_right" sym="climb"/>

  </states>
</model>
