<?xml version="1.0" ?>

<levelsuite>
  <info>
    <title>Monster Tests</title>
    <author>Jakub Pavlik /severus@post.cz/</author>
    <description>
      Testing locations for development of new monster (and not only monster) 
      classes.
    </description>
  </info>

  <theme>TestsTheme</theme>

  <suite>
    <!-- <level>Prototype</level> 
	 Only a template, 
	 really boring for playing, because totally empty -->
    <level>GuardRobot</level>
    <level>WalkingBear</level>
    <level>OrangeHead</level>
    <level>ArrowShooter</level>
    <level>Snail</level>
    <level>Penguin</level>
    <level>ManyItems</level>
    <level>Teleport</level>
    <level>Conversation</level>
    <level>BombEtc</level>
    <level>Ladder</level>
    <level>LivingStone</level>
    <level>SmallStone</level>
    <level>Troll</level>
    <level>FlyingTroll</level>
    <level>LockKeys</level>
  </suite>
</levelsuite>
